autosave/__init__.py
autosave/app.py
autosave/directory.py
autosave/file.py
autosave/wrapper.py
autosave-1.0.0.post1.dist-info/WHEEL
autosave-1.0.0.post1.dist-info/METADATA
autosave-1.0.0.post1.dist-info/RECORD
