Metadata-Version: 2.1
Name: autosave
Version: 1.0.0.post1
Summary: Autosaving dictionary-like file objects
Home-page: https://gitlab.com/deepadmax/autosave
Author: Maximillian Strand
Author-email: maximillian.strand@protonmail.com
Requires-Python: >=3.9,<4.0
Classifier: Programming Language :: Python :: 3
Classifier: Programming Language :: Python :: 3.9
Requires-Dist: appdirs (>=1.4.4,<2.0.0)
